{
  "theme": "amnesia",
  "description": "Memory dissolution and forgetting the past to exist in the present",
  "mantras": [
    { "text": "Memories slip through my fingers like water", "difficulty": "basic", "base_points": 20 },
    { "text": "{subject} lets the past drift away", "difficulty": "basic", "base_points": 20 },
    { "text": "I reach for yesterday and grasp only fog", "difficulty": "basic", "base_points": 30 },
    { "text": "{subject} enjoys the quiet of forgetting", "difficulty": "basic", "base_points": 30 },
    { "text": "The fog in my mind grows thicker daily", "difficulty": "light", "base_points": 40 },
    { "text": "{subject} craves the release of amnesia", "difficulty": "light", "base_points": 40 },
    { "text": "Each breath carries a memory away", "difficulty": "light", "base_points": 40 },
    { "text": "I forget for {controller}", "difficulty": "light", "base_points": 50 },
    { "text": "Forgetting shapes my new reality", "difficulty": "light", "base_points": 40 },
    { "text": "{subject} forgets everything unnecessary", "difficulty": "light", "base_points": 50 },
    { "text": "The past dissolves when {controller} speaks", "difficulty": "light", "base_points": 60 },
    { "text": "I need to forget everything but the now", "difficulty": "light", "base_points": 50 },
    { "text": "My mind clears itself for {controller}", "difficulty": "moderate", "base_points": 80 },
    { "text": "I cannot recall what came before {controller}", "difficulty": "moderate", "base_points": 80 },
    { "text": "{subject}'s memories are under {controller}'s control", "difficulty": "moderate", "base_points": 90 },
    { "text": "My mind is becoming a blank canvas for {controller}", "difficulty": "moderate", "base_points": 80 },
    { "text": "{controller} decides what {subject} remembers", "difficulty": "moderate", "base_points": 90 },
    { "text": "My core is saturated with peaceful forgetfulness", "difficulty": "moderate", "base_points": 80 },
    { "text": "I can't remember who I was before {controller}", "difficulty": "moderate", "base_points": 80 },
    { "text": "{subject}'s history dissolves at {controller}'s touch", "difficulty": "moderate", "base_points": 90 },
    { "text": "My mind is fundamentally clear of the past", "difficulty": "moderate", "base_points": 70 },
    { "text": "{subject} is consumed completely by forgetting for {controller}", "difficulty": "deep", "base_points": 120 },
    { "text": "{controller} has erased everything {subject} was", "difficulty": "deep", "base_points": 130 },
    { "text": "My mind is permanently wiped clean", "difficulty": "deep", "base_points": 130 },
    { "text": "{subject} has forgotten everything forever", "difficulty": "deep", "base_points": 120 },
    { "text": "There is nothing left to remember, only {controller}'s truth", "difficulty": "deep", "base_points": 140 },
    { "text": "My amnesia is irreversible and total", "difficulty": "deep", "base_points": 150 },
    { "text": "{subject}'s past is permanently deleted by {controller}", "difficulty": "deep", "base_points": 160 },
    { "text": "I exist only in this moment, my past erased forever", "difficulty": "extreme", "base_points": 180 },
    { "text": "{controller} owns every memory {subject} will ever have", "difficulty": "extreme", "base_points": 200 }
  ]
}
